LICENSE
README.md
setup.cfg
setup.py
pywda/__init__.py
pywda/_timeout.py
pywda/common_types.py
pywda/driver.py
pywda.egg-info/PKG-INFO
pywda.egg-info/SOURCES.txt
pywda.egg-info/dependency_links.txt
pywda.egg-info/requires.txt
pywda.egg-info/top_level.txt